django_outbox_region/__init__.py
django_outbox_region/asgi.py
django_outbox_region/settings.py
django_outbox_region/urls.py
django_outbox_region/wsgi.py
region/__init__.py
region/admin.py
region/apps.py
region/models.py
region/resources.py
region/tests.py
region/views.py
region/migrations/0001_initial.py
region/migrations/__init__.py
region/templates/admin/import_export/base.html
region/templates/admin/import_export/change_list.html
region/templates/admin/import_export/change_list_export.html
region/templates/admin/import_export/change_list_export_item.html
region/templates/admin/import_export/change_list_import.html
region/templates/admin/import_export/change_list_import_export.html
region/templates/admin/import_export/change_list_import_item.html
region/templates/admin/import_export/export.html
region/templates/admin/import_export/import.html
region/templatetags/__init__.py
region/templatetags/import_export_tags.py
region/templatetags/__pycache__/__init__.cpython-310.pyc
region/templatetags/__pycache__/import_export_tags.cpython-310.pyc
django_outbox_region-1.0.2.dist-info/LICENSE.md
django_outbox_region-1.0.2.dist-info/METADATA
django_outbox_region-1.0.2.dist-info/WHEEL
django_outbox_region-1.0.2.dist-info/top_level.txt
django_outbox_region-1.0.2.dist-info/RECORD
