Metadata-Version: 2.1
Name: django-outbox-region
Version: 1.0.2
Summary: DJANGO OUTBOX REGION
Home-page: https://github.com/PROJECT-OUTBOX/django_lib_outbox_region.git
Author-email: suratiwan03@gmail.com
License: UNKNOWN
Keywords: region,django,country,province,regency,sub district,urban village
Platform: UNKNOWN
Classifier: License :: OSI Approved :: BSD License
Classifier: Intended Audience :: Developers
Classifier: Programming Language :: Python :: 3 :: Only
Requires-Dist: django-import-export
